setup.py
distributions_stats_bigdata/Binomialdistribution.py
distributions_stats_bigdata/Gaussiandistribution.py
distributions_stats_bigdata/Generaldistribution.py
distributions_stats_bigdata/__init__.py
distributions_stats_bigdata.egg-info/PKG-INFO
distributions_stats_bigdata.egg-info/SOURCES.txt
distributions_stats_bigdata.egg-info/dependency_links.txt
distributions_stats_bigdata.egg-info/not-zip-safe
distributions_stats_bigdata.egg-info/top_level.txt