Metadata-Version: 1.0
Name: distributions-stats-bigdata
Version: 0.1
Summary: Gaussian and Binomial distributions
Home-page: UNKNOWN
Author: Jay Patel
Author-email: jay.00174@live.com
License: UNKNOWN
Platform: UNKNOWN
